paitest/__init__.py
paitest/frames/__init__.py
paitest/frames/coord.py
paitest/frames/coord.pyi
paitest/frames/frame.py
paitest/frames/frame_params.py
paitest/log.py
paitest/paitest.py
paitest/paitest.pyi
paitest-1.1.1.dist-info/LICENSE
paitest-1.1.1.dist-info/METADATA
paitest-1.1.1.dist-info/WHEEL
paitest-1.1.1.dist-info/RECORD
