Metadata-Version: 2.1
Name: paitest
Version: 1.1.1
Summary: Test module for PAICORE 2.0
Home-page: https://github.com/PAICookers/PAITest
License: MIT
Keywords: PAICookers,PAITest,PAICORE
Author: KafCoppelia
Author-email: k740677208@gmail.com
Requires-Python: >=3.6,<4.0
Classifier: License :: OSI Approved :: MIT License
Classifier: Programming Language :: Python :: 3
Classifier: Programming Language :: Python :: 3.6
Classifier: Programming Language :: Python :: 3.7
Classifier: Programming Language :: Python :: 3.8
Classifier: Programming Language :: Python :: 3.9
Classifier: Programming Language :: Python :: 3.10
Classifier: Programming Language :: Python :: 3.11
Project-URL: Documentation, https://github.com/PAICookers/PAITest#readme
Project-URL: Repository, https://github.com/PAICookers/PAITest
